battlehack20/__init__.py
battlehack20/stubs.py
battlehack20/basicviewer/__init__.py
battlehack20/basicviewer/viewer.py
battlehack20/container/__init__.py
battlehack20/container/code_container.py
battlehack20/container/runner.py
battlehack20/engine/__init__.py
battlehack20/engine/basicviewer/__init__.py
battlehack20/engine/basicviewer/viewer.py
battlehack20/engine/container/__init__.py
battlehack20/engine/container/code_container.py
battlehack20/engine/container/runner.py
battlehack20/engine/game/__init__.py
battlehack20/engine/game/constants.py
battlehack20/engine/game/game.py
battlehack20/engine/game/robot.py
battlehack20/engine/game/robottype.py
battlehack20/engine/game/team.py
battlehack20/game/__init__.py
battlehack20/game/constants.py
battlehack20/game/game.py
battlehack20/game/robot.py
battlehack20/game/robottype.py
battlehack20/game/team.py
battlehack20_minimal-1.0.6.dist-info/LICENSE
battlehack20_minimal-1.0.6.dist-info/METADATA
battlehack20_minimal-1.0.6.dist-info/WHEEL
battlehack20_minimal-1.0.6.dist-info/top_level.txt
battlehack20_minimal-1.0.6.dist-info/RECORD
