Metadata-Version: 2.1
Name: battlehack20-minimal
Version: 1.0.6
Summary: Battlehack 2020 fancy viewer.
Home-page: https://bh2020.battlecode.org
Author: cooljoseph
Author-email: camacho.joseph@gmail.com
License: GNU General Public License v3.0
Project-URL: Code, https://github.com/cooljoseph1/battlehack20-minimal
Project-URL: Documentation, https://github.com/cooljoseph1/battlehack20-minimal
Platform: UNKNOWN
Requires-Python: >=3, <3.8
